.hgignore
.hgtags
README
setup.py
gpalign/__init__.py
gpalign/__version__.py
gpalign/align.py
gpalign/alignment.py
gpalign/detect_okurigana.py
gpalign/dictionary.py
gpalign/entry.py
gpalign/errors.py
gpalign/evaluate.py
gpalign/format_eval.py
gpalign/frequency.py
gpalign/okurigana_model.py
gpalign/param_search_align.py
gpalign/potentials.py
gpalign/reading_model.py
gpalign/runs.sh
gpalign/settings.py
gpalign/sitecustomize.py
gpalign.egg-info/PKG-INFO
gpalign.egg-info/SOURCES.txt
gpalign.egg-info/dependency_links.txt
gpalign.egg-info/not-zip-safe
gpalign.egg-info/requires.txt
gpalign.egg-info/top_level.txt
gpalign/data/eval-alignment.data
gpalign/tools/profiler.py
gpalign/tools/separate_errors.py
gpalign/tools/strip_kanjidic.py