Metadata-Version: 1.0
Name: gpalign
Version: 0.2.1
Summary: Unsupervised grapheme-phoneme aligner for Japanese
Home-page: http://bitbucket.org/lars512/gpalign-py/
Author: Lars Yencken
Author-email: lljy@csse.unimelb.edu.au
License: BSD
Platform: UNKNOWN
